spectrochempy_omnic/__init__.py
spectrochempy_omnic/__version__.py
spectrochempy_omnic/plugin/__init__.py
spectrochempy_omnic/plugin/omnicreaderplugin.py
spectrochempy_omnic/plugin/utils.py
spectrochempy_omnic/reader/__init__.py
spectrochempy_omnic/reader/read_omnic.py
spectrochempy_omnic-0.2.1.dist-info/licenses/LICENSE
spectrochempy_omnic-0.2.1.dist-info/METADATA
spectrochempy_omnic-0.2.1.dist-info/WHEEL
spectrochempy_omnic-0.2.1.dist-info/entry_points.txt
spectrochempy_omnic-0.2.1.dist-info/top_level.txt
spectrochempy_omnic-0.2.1.dist-info/RECORD
