Metadata-Version: 2.4
Name: spectrochempy-omnic
Version: 0.2.1
Summary: SpectroChemPy OMNIC file reader
Author-email: Arnaud Travert <contact@spectrochempy.fr>, Christian Fernandez <contact@spectrochempy.fr>
License: CeCILL-B FREE SOFTWARE LICENSE AGREEMENT
Project-URL: issues, https://github.com/spectrochempy/spectrochempy-omnic/issues
Project-URL: repository, https://github.com/spectrochempy/spectrochempy-omnic
Keywords: spectroscopy
Classifier: Development Status :: 4 - Beta
Classifier: Topic :: Utilities
Classifier: Topic :: Scientific/Engineering
Classifier: Topic :: Software Development :: Libraries
Classifier: Intended Audience :: Science/Research
Classifier: License :: CeCILL-B Free Software License Agreement (CECILL-B)
Classifier: Operating System :: OS Independent
Classifier: Programming Language :: Python :: 3.10
Classifier: Programming Language :: Python :: 3.11
Classifier: Programming Language :: Python :: 3.12
Classifier: Programming Language :: Python :: 3.13
Requires-Python: >=3.10
License-File: LICENSE
Requires-Dist: numpy
Provides-Extra: build
Requires-Dist: setuptools; extra == "build"
Requires-Dist: setuptools_scm; extra == "build"
Requires-Dist: toml; extra == "build"
Requires-Dist: jinja2; extra == "build"
Requires-Dist: anaconda-client; extra == "build"
Provides-Extra: dev
Requires-Dist: spectrochempy[dev]; extra == "dev"
Provides-Extra: plugin
Requires-Dist: pluggy; extra == "plugin"
Requires-Dist: spectrochempy; extra == "plugin"
Provides-Extra: test
Requires-Dist: requests; extra == "test"
Requires-Dist: pytest; extra == "test"
Requires-Dist: pytest-doctestplus; extra == "test"
Requires-Dist: pytest-ruff; extra == "test"
Dynamic: license-file
